super_gun1k/__init__.py
super_gun1k/main.py
super_gun1k-0.1.0.dist-info/entry_points.txt
super_gun1k-0.1.0.dist-info/WHEEL
super_gun1k-0.1.0.dist-info/METADATA
super_gun1k-0.1.0.dist-info/RECORD
