Metadata-Version: 2.1
Name: super-gun1k
Version: 0.1.0
Summary: 
Author: evan
Author-email: evan@pop-os.localdomain
Requires-Python: >=3.10,<4.0
Classifier: Programming Language :: Python :: 3
Classifier: Programming Language :: Python :: 3.10
Classifier: Programming Language :: Python :: 3.11
Requires-Dist: typer[all] (>=0.7.0,<0.8.0)
